[
  {
    "label": "🔔 חדש! חכם, חסכוני ושימושי, או בקיצור - Clever",
    "subtitle": null,
    "image": "https://www.hvr.co.il/pics/site_home/clever_revile_sld16.gif"
  },
  {
    "label": "🔔 מוכנים? פסטיבל תל אביב EAT חוזר!",
    "subtitle": null,
    "image": "https://www.hvr.co.il/pics/site_home/tel_aviv_eat_sld_200426.jpg"
  },
  {
    "label": "🔔 ממליצים ל\"חבר\"ים ונהנים ממענק עד 1,500 ₪",
    "subtitle": null,
    "image": "https://www.hvr.co.il/pics/site_home/benleumi_ido_sld_300625.jpg"
  },
  {
    "label": "🔔 מרוץ איתן RUN 2026 למען אנשים עם צרכים מיוחדים",
    "subtitle": null,
    "image": "https://www.hvr.co.il/pics/site_home/amutat_eitan26_sld300426.jpg"
  },
  {
    "label": "🛒 \"חבר\" VIP: אביב גפן בפארק הירקון 18.6.26",
    "subtitle": null,
    "url": null,
    "image": "https://www.hvr.co.il/pics/site_home/aviv_vip_med290426.jpg"
  },
  {
    "label": "🛒 \"חבר\" VIP: דודו טסה חוזר לשכונה 2.6.26",
    "subtitle": null,
    "url": null,
    "image": "https://www.hvr.co.il/pics/site_home/vip_tasa2_med_280426.jpg"
  },
  {
    "label": "🛒 \"חבר\" גולדן: פאר טסי בפארק הירקון 28.5.26",
    "subtitle": null,
    "url": null,
    "image": "https://www.hvr.co.il/pics/site_home/peer_tasi_med_280426.jpg"
  },
  {
    "label": "🛒 איתכם ולצידכם: שובר לחנויות H&M",
    "subtitle": null,
    "url": null,
    "image": "https://www.hvr.co.il/pics/site_home/h_and_m_med270426.jpg"
  },
  {
    "label": "🛒 איתכם ולצידכם: מארז קוסמטיקה CARELINE",
    "subtitle": null,
    "url": null,
    "image": "https://www.hvr.co.il/pics/site_home/careline2_med240326.jpg"
  },
  {
    "label": "🛒 כל מה שצריך לחג שבועות טעים",
    "subtitle": null,
    "url": null,
    "image": "https://www.hvr.co.il/pics/site_home/shavuot_med_090522.jpg"
  },
  {
    "label": "🛒 איתכם ולצידכם: מארז מוצרי פסטה ורטבים",
    "subtitle": null,
    "url": null,
    "image": "https://www.hvr.co.il/pics/site_home/diplomat_pasta2_med240326.jpg"
  },
  {
    "label": "🛒 איתכם ולצידכם: מארז מוצרי לוטוס ואוראו",
    "subtitle": null,
    "url": null,
    "image": "https://www.hvr.co.il/pics/site_home/diplomat_lotus_med290426.jpg"
  },
  {
    "label": "🛒 איתכם ולצידכם: מארז פררו רושה וקינדר",
    "subtitle": null,
    "url": null,
    "image": "https://www.hvr.co.il/pics/site_home/diplomat_nutella3_med240326.jpg"
  },
  {
    "label": "🛒 איתכם ולצידכם: עוגת גבינה לבחירה ב-35 ₪",
    "subtitle": null,
    "url": null,
    "image": "https://www.hvr.co.il/pics/site_home/shavuot_neaman_med_270426.jpg"
  },
  {
    "label": "🛒 המוצר המנצח: מכונת גלידה NINJA CREAMI",
    "subtitle": null,
    "url": null,
    "image": "https://www.hvr.co.il/pics/site_home/ninja_icecream_med_270426.jpg"
  },
  {
    "label": "🛒 המוצר המנצח: מיקסר מקצועי מבית סלמור",
    "subtitle": null,
    "url": null,
    "image": "https://www.hvr.co.il/pics/site_home/selmor_mixer_med_b_200426.jpg"
  },
  {
    "label": "🛒 קופוני חג שבועות באפליקציית yellow",
    "subtitle": null,
    "url": null,
    "image": "https://www.hvr.co.il/pics/site_home/yellow_shavuot26_med280426.jpg"
  },
  {
    "label": "🛒 זום ללא עלות: ילדים, מסכים וגבולות",
    "subtitle": null,
    "url": null,
    "image": "https://www.hvr.co.il/pics/site_home/shaat_horut_med290426.jpg"
  },
  {
    "label": "🛒 משלו\"חבר\": 5 חבילות חיתולי BabySitter",
    "subtitle": null,
    "url": null,
    "image": "https://www.hvr.co.il/pics/site_home/babysitter_med240326.jpg"
  },
  {
    "label": "🛒 חדש בנטען! FLOW מותג ביוטי לנערות",
    "subtitle": null,
    "url": null,
    "image": "https://www.hvr.co.il/pics/site_home/flow_med_keva_200426.jpg"
  },
  {
    "label": "🛒 הנחה על מארז 2 חולצות טי + נטען",
    "subtitle": null,
    "url": null,
    "image": "https://www.hvr.co.il/pics/site_home/pulliez_med_keva200426.jpg"
  },
  {
    "label": "🛒 5% הנחה על גבינות ומארזים + \"טעמים\"",
    "subtitle": null,
    "url": null,
    "image": "https://www.hvr.co.il/pics/site_home/melaket_shavotemed_teamim_300426.jpg"
  },
  {
    "label": "🛒 מבצע על מגוון הרכבים של BYD",
    "subtitle": null,
    "url": null,
    "image": "https://www.hvr.co.il/pics/site_home/byd_sealu_med_230326.jpg"
  },
  {
    "label": "🛒 חדש באשראי! מרכז לרפואה סינית פנחסוב",
    "subtitle": null,
    "url": null,
    "image": "https://www.hvr.co.il/pics/site_home/simon_pinhasov_med_blk200426.png"
  },
  {
    "label": "🛒 הנחה על 2 מצלמות אבטחה חכמות",
    "subtitle": null,
    "url": null,
    "image": "https://www.hvr.co.il/pics/site_home/eufy_med_blk200426.png"
  },
  {
    "label": "🛒 מארז BBQ Organic Premium בהנחה",
    "subtitle": null,
    "url": null,
    "image": "https://www.hvr.co.il/pics/site_home/natorapod_med_blk190426.png"
  },
  {
    "label": "🛒 20% הנחה על סדרת הויטרינות החדשות",
    "subtitle": null,
    "url": null,
    "image": "https://www.hvr.co.il/pics/site_home/stelix_med_blk200426.png"
  },
  {
    "label": "🛒 40% הנחה על סטים ומארזים באתר GA-DE",
    "subtitle": null,
    "url": null,
    "image": "https://www.hvr.co.il/pics/site_home/ga_de_med_blk090426.jpg"
  },
  {
    "label": "🛒 חדש באשראי! מלונות רשת NARA",
    "subtitle": null,
    "url": null,
    "image": "https://www.hvr.co.il/pics/site_home/nara_hotels_israc_med_280426.jpg"
  },
  {
    "label": "🛒 חופשה והופעה - סטינג בלימסול בהנחה",
    "subtitle": null,
    "url": null,
    "image": "https://www.hvr.co.il/pics/site_home/tiktik_sting_israc_med_301225.jpg"
  },
  {
    "label": "🛒 100 $ הנחה על טיולים מאורגנים בחו\"ל",
    "subtitle": null,
    "url": null,
    "image": "https://www.hvr.co.il/pics/site_home/fly_trips_israc_med_260426.jpg"
  },
  {
    "label": "🛒 150 € הנחה לחופשה משפחתית בפולין",
    "subtitle": null,
    "url": null,
    "image": "https://www.hvr.co.il/pics/site_home/eshet_poland_israc_med_150426.jpg"
  },
  {
    "label": "🛒 הנחה לטיולים בחו\"ל עם כל המשפחה",
    "subtitle": null,
    "url": null,
    "image": "https://www.hvr.co.il/pics/site_home/mona_batumi_med_140426.jpg"
  },
  {
    "label": "🛒 ביטוח מחלות קשות, בתנאים מיוחדים",
    "subtitle": null,
    "url": null,
    "image": "https://www.hvr.co.il/pics/site_home/mahalot_med_210425.jpg"
  }
]